{
    "id":  "067A",
    "name":  "力的传感器采集",
    "title":  "力的传感器采集系统",
    "devices":  "STM32F103C8T6（主控）、HC-05（蓝牙模块）、HX711（压力传感器，重量）、FSR402（薄膜压力传感器）、OLED 屏幕、按键、蜂鸣器、LED 指示灯、AMS1117-3.3（稳压芯片）",
    "functions":  [
                      "检测：HX711 传感器（0~10kg，精度 ±0.1%）采集重量信号",
                      "检测：FSR402 传感器（0~10N，精度 ±1%）采集压力信号",
                      "检测：采样频率 10Hz~100Hz 可调，覆盖不同力检测场景",
                      "报警：根据力值超限幅度划分三级报警逻辑，通过蜂鸣器发声频率与 LED 闪烁频率差异化提示",
                      "交互：支持本地按键与 APP 同步调节报警阈值",
                      "显示：OLED 屏幕本地实时显示力值数据、工作模式及报警状态",
                      "通信：通过 HC-05 蓝牙模块（传输距离≥10m，延迟≤500ms）上传数据至移动端 APP，支持远程查看与参数同步",
                      "交互：本地按键实现阈值调节、模式切换，APP 远程完成参数修改与报警设置",
                      "校准：系统支持 USB 供电，具备零点误差校准功能，连续工作 2 小时以上稳定性良好"
                  ]
}
